ceilometerclient/__init__.py
ceilometerclient/client.py
ceilometerclient/exc.py
ceilometerclient/i18n.py
ceilometerclient/shell.py
ceilometerclient/apiclient/__init__.py
ceilometerclient/apiclient/auth.py
ceilometerclient/apiclient/base.py
ceilometerclient/apiclient/client.py
ceilometerclient/apiclient/exceptions.py
ceilometerclient/apiclient/fake_client.py
ceilometerclient/apiclient/utils.py
ceilometerclient/common/__init__.py
ceilometerclient/common/base.py
ceilometerclient/common/utils.py
ceilometerclient/tests/__init__.py
ceilometerclient/tests/functional/__init__.py
ceilometerclient/tests/functional/base.py
ceilometerclient/tests/functional/test_readonly_ceilometer.py
ceilometerclient/tests/functional/hooks/post_test_hook.sh
ceilometerclient/tests/unit/__init__.py
ceilometerclient/tests/unit/test_client.py
ceilometerclient/tests/unit/test_exc.py
ceilometerclient/tests/unit/test_openstack_common.py
ceilometerclient/tests/unit/test_shell.py
ceilometerclient/tests/unit/test_utils.py
ceilometerclient/tests/unit/utils.py
ceilometerclient/tests/unit/v2/__init__.py
ceilometerclient/tests/unit/v2/test_alarms.py
ceilometerclient/tests/unit/v2/test_capabilities.py
ceilometerclient/tests/unit/v2/test_event_types.py
ceilometerclient/tests/unit/v2/test_events.py
ceilometerclient/tests/unit/v2/test_options.py
ceilometerclient/tests/unit/v2/test_query_alarm_history.py
ceilometerclient/tests/unit/v2/test_query_alarms.py
ceilometerclient/tests/unit/v2/test_query_samples.py
ceilometerclient/tests/unit/v2/test_resources.py
ceilometerclient/tests/unit/v2/test_samples.py
ceilometerclient/tests/unit/v2/test_shell.py
ceilometerclient/tests/unit/v2/test_statistics.py
ceilometerclient/tests/unit/v2/test_trait_descriptions.py
ceilometerclient/tests/unit/v2/test_traits.py
ceilometerclient/v2/__init__.py
ceilometerclient/v2/alarms.py
ceilometerclient/v2/capabilities.py
ceilometerclient/v2/client.py
ceilometerclient/v2/event_types.py
python_ceilometerclient-2.9.0.dist-info/DESCRIPTION.rst
python_ceilometerclient-2.9.0.dist-info/METADATA
python_ceilometerclient-2.9.0.dist-info/RECORD
python_ceilometerclient-2.9.0.dist-info/WHEEL
python_ceilometerclient-2.9.0.dist-info/entry_points.txt
python_ceilometerclient-2.9.0.dist-info/metadata.json
python_ceilometerclient-2.9.0.dist-info/pbr.json
python_ceilometerclient-2.9.0.dist-info/top_level.txt
